{"startNodeIndex":0.0,"allDialogNodes":[{"xPos":313.80000000000007,"xIn":445.0,"yPos":300.0,"yIn":490.0,"xOut":820.0,"focusedLanuguage":"","yOut":490.0,"out":{"xPos":729.80000000000007,"xIn":861.0,"yPos":302.0,"yIn":492.0,"xOut":1236.0,"focusedLanuguage":"","yOut":492.0,"out":{"xPos":1156.8000000000002,"xIn":1288.0,"yPos":304.0,"yIn":494.0,"xOut":1663.0,"focusedLanuguage":"","yOut":494.0,"out":null,"cursorPos":34.0,"talkers":[{"name":"2","isMirrored":false,"sprite":"@ref sprite(sVN_trickster)","isActive":true,"image":0.0},{"name":"1","isMirrored":true,"sprite":"@ref sprite(sVN_clea)","isActive":false,"image":0.0},{"name":"0","isMirrored":true,"sprite":"@ref sprite(sVN_adam)","isActive":false,"image":0.0}],"languages":[{"key":"EN","content":"#That will be ere the set of sun.#"},{"key":"PL","content":""}],"focusedKey":"EN","in":null,"isGrabbed":false,"inIndex":1.0,"outIndex":-1.0},"cursorPos":1.0,"talkers":[{"name":"0","isMirrored":true,"sprite":"@ref sprite(sVN_adam)","isActive":false,"image":0.0},{"name":"1","isMirrored":false,"sprite":"@ref sprite(sVN_clea)","isActive":true,"image":0.0},{"name":"2","isMirrored":true,"sprite":"@ref sprite(sVN_trickster)","isActive":false,"image":0.0}],"languages":[{"key":"EN","content":"*When the hurly-burly's done*; @when the battle's lost and won@."},{"key":"PL","content":""}],"focusedKey":"PL","in":null,"isGrabbed":false,"inIndex":0.0,"outIndex":2.0},"cursorPos":73.0,"talkers":[{"name":"0","isMirrored":false,"sprite":"@ref sprite(sVN_adam)","isActive":true,"image":0.0},{"name":"2","isMirrored":true,"sprite":"@ref sprite(sVN_trickster)","isActive":false,"image":0.0},{"name":"1","isMirrored":true,"sprite":"@ref sprite(sVN_clea)","isActive":false,"image":0.0}],"languages":[{"key":"EN","content":"When shall we three meet again? In *thunder*, @lightning@, or in #rain#?"},{"key":"PL","content":""}],"focusedKey":"EN","in":null,"isGrabbed":false,"inIndex":-1.0,"outIndex":1.0},{"xPos":729.80000000000007,"xIn":861.0,"yPos":302.0,"yIn":492.0,"xOut":1236.0,"focusedLanuguage":"","yOut":492.0,"out":{"xPos":1156.8000000000002,"xIn":1288.0,"yPos":304.0,"yIn":494.0,"xOut":1663.0,"focusedLanuguage":"","yOut":494.0,"out":null,"cursorPos":34.0,"talkers":[{"name":"2","isMirrored":false,"sprite":"@ref sprite(sVN_trickster)","isActive":true,"image":0.0},{"name":"1","isMirrored":true,"sprite":"@ref sprite(sVN_clea)","isActive":false,"image":0.0},{"name":"0","isMirrored":true,"sprite":"@ref sprite(sVN_adam)","isActive":false,"image":0.0}],"languages":[{"key":"EN","content":"#That will be ere the set of sun.#"},{"key":"PL","content":""}],"focusedKey":"EN","in":null,"isGrabbed":false,"inIndex":1.0,"outIndex":-1.0},"cursorPos":1.0,"talkers":[{"name":"0","isMirrored":true,"sprite":"@ref sprite(sVN_adam)","isActive":false,"image":0.0},{"name":"1","isMirrored":false,"sprite":"@ref sprite(sVN_clea)","isActive":true,"image":0.0},{"name":"2","isMirrored":true,"sprite":"@ref sprite(sVN_trickster)","isActive":false,"image":0.0}],"languages":[{"key":"EN","content":"*When the hurly-burly's done*; @when the battle's lost and won@."},{"key":"PL","content":""}],"focusedKey":"PL","in":{"xPos":313.80000000000007,"xIn":445.0,"yPos":300.0,"yIn":490.0,"xOut":820.0,"focusedLanuguage":"","yOut":490.0,"out":null,"cursorPos":73.0,"talkers":[{"name":"0","isMirrored":false,"sprite":"@ref sprite(sVN_adam)","isActive":true,"image":0.0},{"name":"2","isMirrored":true,"sprite":"@ref sprite(sVN_trickster)","isActive":false,"image":0.0},{"name":"1","isMirrored":true,"sprite":"@ref sprite(sVN_clea)","isActive":false,"image":0.0}],"languages":[{"key":"EN","content":"When shall we three meet again? In *thunder*, @lightning@, or in #rain#?"},{"key":"PL","content":""}],"focusedKey":"EN","in":null,"isGrabbed":false,"inIndex":-1.0,"outIndex":1.0},"isGrabbed":false,"inIndex":0.0,"outIndex":2.0},{"xPos":1156.8000000000002,"xIn":1288.0,"yPos":304.0,"yIn":494.0,"xOut":1663.0,"focusedLanuguage":"","yOut":494.0,"out":null,"cursorPos":34.0,"talkers":[{"name":"2","isMirrored":false,"sprite":"@ref sprite(sVN_trickster)","isActive":true,"image":0.0},{"name":"1","isMirrored":true,"sprite":"@ref sprite(sVN_clea)","isActive":false,"image":0.0},{"name":"0","isMirrored":true,"sprite":"@ref sprite(sVN_adam)","isActive":false,"image":0.0}],"languages":[{"key":"EN","content":"#That will be ere the set of sun.#"},{"key":"PL","content":""}],"focusedKey":"EN","in":{"xPos":729.80000000000007,"xIn":861.0,"yPos":302.0,"yIn":492.0,"xOut":1236.0,"focusedLanuguage":"","yOut":492.0,"out":null,"cursorPos":1.0,"talkers":[{"name":"0","isMirrored":true,"sprite":"@ref sprite(sVN_adam)","isActive":false,"image":0.0},{"name":"1","isMirrored":false,"sprite":"@ref sprite(sVN_clea)","isActive":true,"image":0.0},{"name":"2","isMirrored":true,"sprite":"@ref sprite(sVN_trickster)","isActive":false,"image":0.0}],"languages":[{"key":"EN","content":"*When the hurly-burly's done*; @when the battle's lost and won@."},{"key":"PL","content":""}],"focusedKey":"PL","in":{"xPos":313.80000000000007,"xIn":445.0,"yPos":300.0,"yIn":490.0,"xOut":820.0,"focusedLanuguage":"","yOut":490.0,"out":null,"cursorPos":73.0,"talkers":[{"name":"0","isMirrored":false,"sprite":"@ref sprite(sVN_adam)","isActive":true,"image":0.0},{"name":"2","isMirrored":true,"sprite":"@ref sprite(sVN_trickster)","isActive":false,"image":0.0},{"name":"1","isMirrored":true,"sprite":"@ref sprite(sVN_clea)","isActive":false,"image":0.0}],"languages":[{"key":"EN","content":"When shall we three meet again? In *thunder*, @lightning@, or in #rain#?"},{"key":"PL","content":""}],"focusedKey":"EN","in":null,"isGrabbed":false,"inIndex":-1.0,"outIndex":1.0},"isGrabbed":false,"inIndex":0.0,"outIndex":2.0},"isGrabbed":false,"inIndex":1.0,"outIndex":-1.0}]}
